{
  "placeholderImages": [
    {
      "id": "hero-bg",
      "description": "Abstract dark cloud computing background with neon purple gradients",
      "imageUrl": "https://picsum.photos/seed/aws-purple-bg/1200/800",
      "imageHint": "purple cloud computing"
    },
    {
      "id": "club-logo",
      "description": "AWS Cloud Club MRIT Official Logo - Purple cloud with stars and AWS smile",
      "imageUrl": "https://picsum.photos/seed/mrit-purple-logo/400/400",
      "imageHint": "purple cloud logo"
    },
    {
      "id": "team-captain",
      "description": "Profile of club captain Zubeda Yasmeen",
      "imageUrl": "https://picsum.photos/seed/female-captain/400/400",
      "imageHint": "professional woman"
    },
    {
      "id": "team-tech",
      "description": "Profile placeholder for technology leadership",
      "imageUrl": "https://picsum.photos/seed/male-tech/400/400",
      "imageHint": "tech expert"
    },
    {
      "id": "team-event",
      "description": "Profile of event lead Yasmeen Taj",
      "imageUrl": "https://picsum.photos/seed/female-event/400/400",
      "imageHint": "manager woman"
    },
    {
      "id": "team-logistics",
      "description": "Profile placeholder for logistics leadership",
      "imageUrl": "https://picsum.photos/seed/female-logistics/400/400",
      "imageHint": "smiling woman"
    },
    {
      "id": "team-doc",
      "description": "Umme Salma - young woman with dark hair, wearing a patterned navy blue and white top, posing in front of lush pink flowers and green foliage against a clear sky background.",
      "imageUrl": "https://picsum.photos/seed/umme-salma-floral/400/400",
      "imageHint": "woman flowers"
    },
    {
      "id": "faculty-harshitha",
      "description": "Ms. Harshitha M - Assistant Professor, Dept of CSE",
      "imageUrl": "https://picsum.photos/seed/faculty-harshitha/400/400",
      "imageHint": "professor woman"
    },
    {
      "id": "faculty-sariya",
      "description": "Ms. Sariya Anjum - Faculty Coordinator, Dept of CSE",
      "imageUrl": "https://picsum.photos/seed/faculty-sariya/400/400",
      "imageHint": "professor woman"
    },
    {
      "id": "faculty-gowtham",
      "description": "Mr. Gowtham A R - Faculty Coordinator, Dept of CSE",
      "imageUrl": "https://picsum.photos/seed/faculty-gowtham/400/400",
      "imageHint": "professor man"
    },
    {
      "id": "faculty-seema",
      "description": "Profile of faculty coordinator Seema Firdous",
      "imageUrl": "https://picsum.photos/seed/faculty-seema/400/400",
      "imageHint": "professor woman"
    },
    {
      "id": "member-gen-1",
      "description": "Generic member profile 1",
      "imageUrl": "https://picsum.photos/seed/m1/400/400",
      "imageHint": "student profile"
    },
    {
      "id": "member-gen-2",
      "description": "Generic member profile 2",
      "imageUrl": "https://picsum.photos/seed/m2/400/400",
      "imageHint": "student profile"
    },
    {
      "id": "member-gen-3",
      "description": "Generic member profile 3",
      "imageUrl": "https://picsum.photos/seed/m3/400/400",
      "imageHint": "student profile"
    },
    {
      "id": "member-gen-4",
      "description": "Generic member profile 4",
      "imageUrl": "https://picsum.photos/seed/m4/400/400",
      "imageHint": "student profile"
    },
    {
      "id": "member-gen-5",
      "description": "Generic member profile 5",
      "imageUrl": "https://picsum.photos/seed/m5/400/400",
      "imageHint": "student profile"
    },
    {
      "id": "member-gen-6",
      "description": "Generic member profile 6",
      "imageUrl": "https://picsum.photos/seed/m6/400/400",
      "imageHint": "student profile"
    },
    {
      "id": "member-gen-7",
      "description": "Generic member profile 7",
      "imageUrl": "https://picsum.photos/seed/m7/400/400",
      "imageHint": "student profile"
    },
    {
      "id": "member-gen-8",
      "description": "Generic member profile 8",
      "imageUrl": "https://picsum.photos/seed/m8/400/400",
      "imageHint": "student profile"
    },
    {
      "id": "member-gen-9",
      "description": "Generic member profile 9",
      "imageUrl": "https://picsum.photos/seed/m9/400/400",
      "imageHint": "student profile"
    },
    {
      "id": "event-inauguration",
      "description": "Official Club Inauguration Ceremony",
      "imageUrl": "https://picsum.photos/seed/inauguration/600/400",
      "imageHint": "grand opening"
    },
    {
      "id": "event-aws-discovery",
      "description": "AWS Discovery Day",
      "imageUrl": "https://picsum.photos/seed/event1/600/400",
      "imageHint": "workshop conference"
    },
    {
      "id": "event-cloud-jam",
      "description": "Cloud Jam Workshop",
      "imageUrl": "https://picsum.photos/seed/event2/600/400",
      "imageHint": "coding session"
    },
    {
      "id": "event-launch",
      "description": "Official Club Launch and Ceremony",
      "imageUrl": "https://picsum.photos/seed/club-launch/600/400",
      "imageHint": "celebration ceremony"
    }
  ]
}